aleph_lang/__init__.py
aleph_lang/kets.py
aleph_lang-0.9.0.dist-info/METADATA
aleph_lang-0.9.0.dist-info/WHEEL
aleph_lang-0.9.0.dist-info/top_level.txt
aleph_lang-0.9.0.dist-info/RECORD
