Metadata-Version: 2.1
Name: aleph-lang
Version: 0.9.0
Summary: Python bindings for aleph, a high level programming model that can be embedded into classical languages to develop large scale quantum hybrid applications, without the quantum mechanics.
Home-page: https://github.com/anpaz/aleph
Author: Andrés Paz
Author-email: anpaz@cs.washington.edu
Classifier: Programming Language :: Python :: 3
Classifier: License :: OSI Approved :: MIT License
Classifier: Operating System :: OS Independent
Requires-Dist: requests
